splusdata/__init__.py
splusdata/connect.py
splusdata/core.py
splusdata/readconf.py
splusdata/vars.py
splusdata/features/__init__.py
splusdata/features/extinction.py
splusdata/features/filterbw.py
splusdata/features/find_pointings.py
splusdata/features/hipscat.py
splusdata/features/io.py
splusdata/features/zeropointsdr4.py
splusdata/features/zeropoints/__init__.py
splusdata/features/zeropoints/zp_image.py
splusdata/features/zeropoints/zp_map.py
splusdata/models/__init__.py
splusdata/models/star_gal_quasar.py
splusdata/scripts/args.py
splusdata/scripts/utils.py
splusdata/scubes/__init__.py
splusdata/scubes/core.py
splusdata/scubes/read.py
splusdata/scubes/scripts.py
splusdata/vacs/__init__.py
splusdata/vacs/pdfs.py
splusdata/vacs/sqg.py
splusdata/variability/__init__.py
splusdata-5.49.dist-info/licenses/LICENSE
splusdata-5.49.dist-info/METADATA
splusdata-5.49.dist-info/WHEEL
splusdata-5.49.dist-info/entry_points.txt
splusdata-5.49.dist-info/top_level.txt
splusdata-5.49.dist-info/RECORD
