Metadata-Version: 2.4
Name: splusdata
Version: 5.49
Summary: Download SPLUS catalogs, FITS and more
Author-email: Gustavo Schwarz <gustavo.b.schwarz@gmail.com>
License: Apache-2.0
Keywords: S-PLUS,astronomy,catalogs,FITS
Classifier: Programming Language :: Python :: 3
Classifier: License :: OSI Approved :: Apache Software License
Requires-Python: >=3.7
License-File: LICENSE
Requires-Dist: adss>=1.36
Requires-Dist: requests
Requires-Dist: astropy
Requires-Dist: astroquery
Requires-Dist: numpy
Requires-Dist: pandas
Requires-Dist: scipy
Requires-Dist: pillow
Requires-Dist: pyyaml
Requires-Dist: tqdm
Dynamic: license-file
